{
  "machine": "NVIDIA GeForce RTX 4090",
  "cases": [
    {
      "spec": "rmsnorm",
      "kernel": "rmsnorm.py",
      "label": "GOLD",
      "expect": "ok",
      "got": "ok",
      "pass": true,
      "status": "ok",
      "feedback": "PASS 12 cases | 0.1597ms | 8.13x eager, 1.15x compile, 1.13x max-autotune",
      "correct": true,
      "n_shapes_passed": 12,
      "max_abs_err": 0.0625,
      "latency_ms": 0.15974,
      "eager_ms": 1.29843,
      "compile_ms": 0.1833,
      "maxauto_ms": 0.18022,
      "speedup_eager": 8.1282,
      "speedup_compile": 1.1474,
      "speedup_maxauto": 1.1282
    },
    {
      "spec": "softmax",
      "kernel": "softmax.py",
      "label": "GOLD",
      "expect": "ok",
      "got": "ok",
      "pass": true,
      "status": "ok",
      "feedback": "PASS 12 cases | 0.1606ms | 4.54x eager, 1.12x compile, 1.12x max-autotune",
      "correct": true,
      "n_shapes_passed": 12,
      "max_abs_err": 1.52587890625e-05,
      "latency_ms": 0.16061,
      "eager_ms": 0.72907,
      "compile_ms": 0.18005,
      "maxauto_ms": 0.17917,
      "speedup_eager": 4.5395,
      "speedup_compile": 1.121,
      "speedup_maxauto": 1.1156
    },
    {
      "spec": "swiglu",
      "kernel": "swiglu.py",
      "label": "GOLD",
      "expect": "ok",
      "got": "ok",
      "pass": true,
      "status": "ok",
      "feedback": "PASS 11 cases | 0.2294ms | 6.04x eager, 1.11x compile, 1.10x max-autotune",
      "correct": true,
      "n_shapes_passed": 11,
      "max_abs_err": 0.015625,
      "latency_ms": 0.22938,
      "eager_ms": 1.3865,
      "compile_ms": 0.25395,
      "maxauto_ms": 0.25293,
      "speedup_eager": 6.0446,
      "speedup_compile": 1.1071,
      "speedup_maxauto": 1.1027
    },
    {
      "spec": "add_rmsnorm",
      "kernel": "add_rmsnorm.py",
      "label": "GOLD",
      "expect": "ok",
      "got": "ok",
      "pass": true,
      "status": "ok",
      "feedback": "PASS 11 cases | 0.2303ms | 8.49x eager, 1.10x compile, 1.10x max-autotune",
      "correct": true,
      "n_shapes_passed": 11,
      "max_abs_err": 0.0625,
      "latency_ms": 0.23034,
      "eager_ms": 1.95584,
      "compile_ms": 0.25293,
      "maxauto_ms": 0.25242,
      "speedup_eager": 8.4912,
      "speedup_compile": 1.0981,
      "speedup_maxauto": 1.0959
    },
    {
      "spec": "rope",
      "kernel": "rope.py",
      "label": "GOLD",
      "expect": "ok",
      "got": "ok",
      "pass": true,
      "status": "ok",
      "feedback": "PASS 12 cases | 0.0358ms | 4.93x eager, 1.29x compile, 1.26x max-autotune",
      "correct": true,
      "n_shapes_passed": 12,
      "max_abs_err": 3.0517578125e-05,
      "latency_ms": 0.03584,
      "eager_ms": 0.17686,
      "compile_ms": 0.04608,
      "maxauto_ms": 0.04506,
      "speedup_eager": 4.9348,
      "speedup_compile": 1.2857,
      "speedup_maxauto": 1.2571
    },
    {
      "spec": "layernorm",
      "kernel": "layernorm.py",
      "label": "GOLD",
      "expect": "ok",
      "got": "ok",
      "pass": true,
      "status": "ok",
      "feedback": "PASS 11 cases | 0.1628ms | 13.21x eager, 1.10x compile, 1.11x max-autotune",
      "correct": true,
      "n_shapes_passed": 11,
      "max_abs_err": 0.0078125,
      "latency_ms": 0.16282,
      "eager_ms": 2.15102,
      "compile_ms": 0.1792,
      "maxauto_ms": 0.18008,
      "speedup_eager": 13.2114,
      "speedup_compile": 1.1006,
      "speedup_maxauto": 1.106
    },
    {
      "spec": "add_layernorm",
      "kernel": "add_layernorm.py",
      "label": "GOLD",
      "expect": "ok",
      "got": "ok",
      "pass": true,
      "status": "ok",
      "feedback": "PASS 11 cases | 0.2365ms | 11.90x eager, 1.07x compile, 1.06x max-autotune",
      "correct": true,
      "n_shapes_passed": 11,
      "max_abs_err": 0.00390625,
      "latency_ms": 0.23654,
      "eager_ms": 2.81539,
      "compile_ms": 0.25267,
      "maxauto_ms": 0.25154,
      "speedup_eager": 11.9022,
      "speedup_compile": 1.0682,
      "speedup_maxauto": 1.0634
    },
    {
      "spec": "geglu",
      "kernel": "geglu.py",
      "label": "GOLD",
      "expect": "ok",
      "got": "ok",
      "pass": true,
      "status": "ok",
      "feedback": "PASS 11 cases | 0.2304ms | 18.61x eager, 1.09x compile, 1.11x max-autotune",
      "correct": true,
      "n_shapes_passed": 11,
      "max_abs_err": 0.125,
      "latency_ms": 0.2304,
      "eager_ms": 4.28886,
      "compile_ms": 0.25088,
      "maxauto_ms": 0.25491,
      "speedup_eager": 18.6149,
      "speedup_compile": 1.0889,
      "speedup_maxauto": 1.1064
    },
    {
      "spec": "qknorm_rope",
      "kernel": "qknorm_rope.py",
      "label": "GOLD (fusion chain)",
      "expect": "ok",
      "got": "ok",
      "pass": true,
      "status": "ok",
      "feedback": "PASS 12 cases | 0.0430ms | 5.47x eager, 1.29x compile, 1.31x max-autotune",
      "correct": true,
      "n_shapes_passed": 12,
      "max_abs_err": 0.001953125,
      "latency_ms": 0.04301,
      "eager_ms": 0.23523,
      "compile_ms": 0.0553,
      "maxauto_ms": 0.05632,
      "speedup_eager": 5.4695,
      "speedup_compile": 1.2857,
      "speedup_maxauto": 1.3095
    },
    {
      "spec": "softcap_softmax",
      "kernel": "softcap_softmax.py",
      "label": "GOLD (Gemma2 softcap)",
      "expect": "ok",
      "got": "ok",
      "pass": true,
      "status": "ok",
      "feedback": "PASS 12 cases | 0.1608ms | 9.97x eager, 1.11x compile, 1.11x max-autotune",
      "correct": true,
      "n_shapes_passed": 12,
      "max_abs_err": 0.0009765625,
      "latency_ms": 0.16077,
      "eager_ms": 1.60358,
      "compile_ms": 0.17789,
      "maxauto_ms": 0.17907,
      "speedup_eager": 9.9745,
      "speedup_compile": 1.1065,
      "speedup_maxauto": 1.1139
    },
    {
      "spec": "rmsnorm_gemma",
      "kernel": "rmsnorm_gemma.py",
      "label": "GOLD (Gemma 1+w)",
      "expect": "ok",
      "got": "ok",
      "pass": true,
      "status": "ok",
      "feedback": "PASS 12 cases | 0.1638ms | 8.87x eager, 1.09x compile, 1.10x max-autotune",
      "correct": true,
      "n_shapes_passed": 12,
      "max_abs_err": 0.03125,
      "latency_ms": 0.16384,
      "eager_ms": 1.45384,
      "compile_ms": 0.1792,
      "maxauto_ms": 0.18006,
      "speedup_eager": 8.8735,
      "speedup_compile": 1.0937,
      "speedup_maxauto": 1.099
    },
    {
      "spec": "glu",
      "kernel": "glu.py",
      "label": "GOLD (original GLU)",
      "expect": "ok",
      "got": "ok",
      "pass": true,
      "status": "ok",
      "feedback": "PASS 11 cases | 0.2314ms | 5.99x eager, 1.09x compile, 1.09x max-autotune",
      "correct": true,
      "n_shapes_passed": 11,
      "max_abs_err": 0.001953125,
      "latency_ms": 0.23142,
      "eager_ms": 1.38525,
      "compile_ms": 0.25293,
      "maxauto_ms": 0.25264,
      "speedup_eager": 5.9858,
      "speedup_compile": 1.0929,
      "speedup_maxauto": 1.0917
    },
    {
      "spec": "rope_interleaved",
      "kernel": "rope_interleaved.py",
      "label": "GOLD (GPT-J RoPE)",
      "expect": "ok",
      "got": "ok",
      "pass": true,
      "status": "ok",
      "feedback": "PASS 12 cases | 0.0348ms | 4.63x eager, 1.38x compile, 1.52x max-autotune",
      "correct": true,
      "n_shapes_passed": 12,
      "max_abs_err": 3.0517578125e-05,
      "latency_ms": 0.03482,
      "eager_ms": 0.16118,
      "compile_ms": 0.04813,
      "maxauto_ms": 0.05302,
      "speedup_eager": 4.6296,
      "speedup_compile": 1.3824,
      "speedup_maxauto": 1.523
    },
    {
      "spec": "cross_entropy",
      "kernel": "cross_entropy.py",
      "label": "GOLD (fused CE)",
      "expect": "ok",
      "got": "ok",
      "pass": true,
      "status": "ok",
      "feedback": "PASS 12 cases | 0.0376ms | 13.85x eager, 2.62x compile, 2.64x max-autotune",
      "correct": true,
      "n_shapes_passed": 12,
      "max_abs_err": 3.0517578125e-05,
      "latency_ms": 0.03763,
      "eager_ms": 0.52122,
      "compile_ms": 0.09866,
      "maxauto_ms": 0.09922,
      "speedup_eager": 13.8503,
      "speedup_compile": 2.6216,
      "speedup_maxauto": 2.6365
    },
    {
      "spec": "cumsum",
      "kernel": "cumsum.py",
      "label": "GOLD (prefix scan)",
      "expect": "ok",
      "got": "ok",
      "pass": true,
      "status": "ok",
      "feedback": "PASS 12 cases | 0.1577ms | 4.95x eager, 1.16x compile, 1.16x max-autotune",
      "correct": true,
      "n_shapes_passed": 12,
      "max_abs_err": 4.0,
      "latency_ms": 0.1577,
      "eager_ms": 0.78029,
      "compile_ms": 0.18227,
      "maxauto_ms": 0.18227,
      "speedup_eager": 4.9481,
      "speedup_compile": 1.1558,
      "speedup_maxauto": 1.1558
    },
    {
      "spec": "entropy",
      "kernel": "entropy.py",
      "label": "GOLD (entropy-from-logits)",
      "expect": "ok",
      "got": "ok",
      "pass": true,
      "status": "ok",
      "feedback": "PASS 12 cases | 0.0398ms | 55.36x eager, 2.47x compile, 2.49x max-autotune",
      "correct": true,
      "n_shapes_passed": 12,
      "max_abs_err": 0.015625,
      "latency_ms": 0.03982,
      "eager_ms": 2.20461,
      "compile_ms": 0.09818,
      "maxauto_ms": 0.09931,
      "speedup_eager": 55.3588,
      "speedup_compile": 2.4652,
      "speedup_maxauto": 2.4938
    },
    {
      "spec": "kl_div",
      "kernel": "kl_div.py",
      "label": "GOLD (logit-pair KL)",
      "expect": "ok",
      "got": "ok",
      "pass": true,
      "status": "ok",
      "feedback": "PASS 12 cases | 0.1729ms | 23.24x eager, 1.05x compile, 1.40x max-autotune",
      "correct": true,
      "n_shapes_passed": 12,
      "max_abs_err": 0.125,
      "latency_ms": 0.17286,
      "eager_ms": 4.01818,
      "compile_ms": 0.18067,
      "maxauto_ms": 0.24242,
      "speedup_eager": 23.2447,
      "speedup_compile": 1.0452,
      "speedup_maxauto": 1.4024
    },
    {
      "spec": "rmsnorm",
      "kernel": "rmsnorm_wrong.py",
      "label": "NEGATIVE-CONTROL (no rsqrt)",
      "expect": "incorrect",
      "got": "incorrect",
      "pass": true,
      "status": "incorrect",
      "feedback": "max abs err inf on (37, 4097)/torch.float16 scale~304 (151588 elems over tol 2.0e-03/2.0e-02) \u2014 likely a reduction/stability bug, not a shape bug",
      "correct": false,
      "n_shapes_passed": 0,
      "max_abs_err": Infinity,
      "latency_ms": 0.0,
      "eager_ms": 0.0,
      "compile_ms": 0.0,
      "maxauto_ms": 0.0,
      "speedup_eager": 0.0,
      "speedup_compile": 0.0,
      "speedup_maxauto": 0.0
    },
    {
      "spec": "softmax",
      "kernel": "softmax_wrong.py",
      "label": "NEGATIVE-CONTROL (no max-subtract)",
      "expect": "incorrect",
      "got": "incorrect",
      "pass": true,
      "status": "incorrect",
      "feedback": "max abs err nan on (37, 4097)/torch.float16 scale~304 (0 elems over tol 2.0e-03/2.0e-02) \u2014 likely a reduction/stability bug, not a shape bug",
      "correct": false,
      "n_shapes_passed": 0,
      "max_abs_err": NaN,
      "latency_ms": 0.0,
      "eager_ms": 0.0,
      "compile_ms": 0.0,
      "maxauto_ms": 0.0,
      "speedup_eager": 0.0,
      "speedup_compile": 0.0,
      "speedup_maxauto": 0.0
    },
    {
      "spec": "add_rmsnorm",
      "kernel": "add_rmsnorm_wrong.py",
      "label": "NEGATIVE-CONTROL (drops residual in stat)",
      "expect": "incorrect",
      "got": "incorrect",
      "pass": true,
      "status": "incorrect",
      "feedback": "max abs err 4.477e+00 on (37, 4097)/torch.float16 scale~304 (148483 elems over tol 2.0e-03/2.0e-02) \u2014 likely a reduction/stability bug, not a shape bug",
      "correct": false,
      "n_shapes_passed": 0,
      "max_abs_err": 4.4765625,
      "latency_ms": 0.0,
      "eager_ms": 0.0,
      "compile_ms": 0.0,
      "maxauto_ms": 0.0,
      "speedup_eager": 0.0,
      "speedup_compile": 0.0,
      "speedup_maxauto": 0.0
    },
    {
      "spec": "rope",
      "kernel": "rope_wrong.py",
      "label": "NEGATIVE-CONTROL (drops rotate_half negation)",
      "expect": "incorrect",
      "got": "incorrect",
      "pass": true,
      "status": "incorrect",
      "feedback": "max abs err 4.041e+02 on (37, 128)/torch.float16 scale~223 (2303 elems over tol 2.0e-03/2.0e-02) \u2014 likely a reduction/stability bug, not a shape bug",
      "correct": false,
      "n_shapes_passed": 0,
      "max_abs_err": 404.125,
      "latency_ms": 0.0,
      "eager_ms": 0.0,
      "compile_ms": 0.0,
      "maxauto_ms": 0.0,
      "speedup_eager": 0.0,
      "speedup_compile": 0.0,
      "speedup_maxauto": 0.0
    },
    {
      "spec": "layernorm",
      "kernel": "layernorm_wrong.py",
      "label": "NEGATIVE-CONTROL (no mean-subtraction)",
      "expect": "incorrect",
      "got": "incorrect",
      "pass": true,
      "status": "incorrect",
      "feedback": "max abs err 1.470e-01 on (37, 4097)/torch.float16 scale~304 (29879 elems over tol 2.0e-03/2.0e-02) \u2014 likely a reduction/stability bug, not a shape bug",
      "correct": false,
      "n_shapes_passed": 0,
      "max_abs_err": 0.14697265625,
      "latency_ms": 0.0,
      "eager_ms": 0.0,
      "compile_ms": 0.0,
      "maxauto_ms": 0.0,
      "speedup_eager": 0.0,
      "speedup_compile": 0.0,
      "speedup_maxauto": 0.0
    },
    {
      "spec": "add_layernorm",
      "kernel": "add_layernorm_wrong.py",
      "label": "NEGATIVE-CONTROL (drops residual in stat)",
      "expect": "incorrect",
      "got": "incorrect",
      "pass": true,
      "status": "incorrect",
      "feedback": "max abs err 4.320e+00 on (37, 4097)/torch.float16 scale~304 (134154 elems over tol 2.0e-03/2.0e-02) \u2014 likely a reduction/stability bug, not a shape bug",
      "correct": false,
      "n_shapes_passed": 0,
      "max_abs_err": 4.3203125,
      "latency_ms": 0.0,
      "eager_ms": 0.0,
      "compile_ms": 0.0,
      "maxauto_ms": 0.0,
      "speedup_eager": 0.0,
      "speedup_compile": 0.0,
      "speedup_maxauto": 0.0
    },
    {
      "spec": "geglu",
      "kernel": "geglu_wrong.py",
      "label": "NEGATIVE-CONTROL (SiLU instead of GELU)",
      "expect": "incorrect",
      "got": "incorrect",
      "pass": true,
      "status": "incorrect",
      "feedback": "max abs err 5.812e+00 on (37, 4097)/torch.float16 scale~304 (12779 elems over tol 2.0e-03/2.0e-02) \u2014 likely a reduction/stability bug, not a shape bug",
      "correct": false,
      "n_shapes_passed": 0,
      "max_abs_err": 5.8125,
      "latency_ms": 0.0,
      "eager_ms": 0.0,
      "compile_ms": 0.0,
      "maxauto_ms": 0.0,
      "speedup_eager": 0.0,
      "speedup_compile": 0.0,
      "speedup_maxauto": 0.0
    },
    {
      "spec": "qknorm_rope",
      "kernel": "qknorm_rope_wrong.py",
      "label": "NEGATIVE-CONTROL (rms scale dropped on rotated half)",
      "expect": "incorrect",
      "got": "incorrect",
      "pass": true,
      "status": "incorrect",
      "feedback": "max abs err 3.147e+02 on (37, 128)/torch.float16 scale~220 (4705 elems over tol 2.0e-03/2.0e-02) \u2014 likely a reduction/stability bug, not a shape bug",
      "correct": false,
      "n_shapes_passed": 0,
      "max_abs_err": 314.70703125,
      "latency_ms": 0.0,
      "eager_ms": 0.0,
      "compile_ms": 0.0,
      "maxauto_ms": 0.0,
      "speedup_eager": 0.0,
      "speedup_compile": 0.0,
      "speedup_maxauto": 0.0
    },
    {
      "spec": "softcap_softmax",
      "kernel": "softcap_softmax_wrong.py",
      "label": "NEGATIVE-CONTROL (no softcap)",
      "expect": "incorrect",
      "got": "incorrect",
      "pass": true,
      "status": "incorrect",
      "feedback": "max abs err 9.985e-01 on (37, 4097)/torch.float16 scale~304 (53 elems over tol 2.0e-03/2.0e-02) \u2014 likely a reduction/stability bug, not a shape bug",
      "correct": false,
      "n_shapes_passed": 0,
      "max_abs_err": 0.9984798431396484,
      "latency_ms": 0.0,
      "eager_ms": 0.0,
      "compile_ms": 0.0,
      "maxauto_ms": 0.0,
      "speedup_eager": 0.0,
      "speedup_compile": 0.0,
      "speedup_maxauto": 0.0
    },
    {
      "spec": "rmsnorm_gemma",
      "kernel": "rmsnorm_gemma_wrong.py",
      "label": "NEGATIVE-CONTROL (drops the +1)",
      "expect": "incorrect",
      "got": "incorrect",
      "pass": true,
      "status": "incorrect",
      "feedback": "max abs err 4.754e+00 on (37, 4097)/torch.float16 scale~304 (151339 elems over tol 2.0e-03/2.0e-02) \u2014 likely a reduction/stability bug, not a shape bug",
      "correct": false,
      "n_shapes_passed": 0,
      "max_abs_err": 4.75390625,
      "latency_ms": 0.0,
      "eager_ms": 0.0,
      "compile_ms": 0.0,
      "maxauto_ms": 0.0,
      "speedup_eager": 0.0,
      "speedup_compile": 0.0,
      "speedup_maxauto": 0.0
    },
    {
      "spec": "glu",
      "kernel": "glu_wrong.py",
      "label": "NEGATIVE-CONTROL (silu not sigmoid)",
      "expect": "incorrect",
      "got": "incorrect",
      "pass": true,
      "status": "incorrect",
      "feedback": "max abs err 4.818e+03 on (37, 4097)/torch.float16 scale~288 (84947 elems over tol 2.0e-03/2.0e-02) \u2014 likely a reduction/stability bug, not a shape bug",
      "correct": false,
      "n_shapes_passed": 0,
      "max_abs_err": 4817.9375,
      "latency_ms": 0.0,
      "eager_ms": 0.0,
      "compile_ms": 0.0,
      "maxauto_ms": 0.0,
      "speedup_eager": 0.0,
      "speedup_compile": 0.0,
      "speedup_maxauto": 0.0
    },
    {
      "spec": "rope_interleaved",
      "kernel": "rope_interleaved_wrong.py",
      "label": "NEGATIVE-CONTROL (drops negation)",
      "expect": "incorrect",
      "got": "incorrect",
      "pass": true,
      "status": "incorrect",
      "feedback": "max abs err 4.062e+02 on (37, 128)/torch.float16 scale~260 (2306 elems over tol 2.0e-03/2.0e-02) \u2014 likely a reduction/stability bug, not a shape bug",
      "correct": false,
      "n_shapes_passed": 0,
      "max_abs_err": 406.25,
      "latency_ms": 0.0,
      "eager_ms": 0.0,
      "compile_ms": 0.0,
      "maxauto_ms": 0.0,
      "speedup_eager": 0.0,
      "speedup_compile": 0.0,
      "speedup_maxauto": 0.0
    },
    {
      "spec": "cross_entropy",
      "kernel": "cross_entropy_wrong.py",
      "label": "NEGATIVE-CONTROL (no max-subtract)",
      "expect": "incorrect",
      "got": "incorrect",
      "pass": true,
      "status": "incorrect",
      "feedback": "max abs err inf on (37, 4097)/torch.float16 scale~282 (37 elems over tol 2.0e-03/2.0e-02) \u2014 likely a reduction/stability bug, not a shape bug",
      "correct": false,
      "n_shapes_passed": 0,
      "max_abs_err": Infinity,
      "latency_ms": 0.0,
      "eager_ms": 0.0,
      "compile_ms": 0.0,
      "maxauto_ms": 0.0,
      "speedup_eager": 0.0,
      "speedup_compile": 0.0,
      "speedup_maxauto": 0.0
    },
    {
      "spec": "cumsum",
      "kernel": "cumsum_wrong.py",
      "label": "NEGATIVE-CONTROL (no carry across blocks)",
      "expect": "incorrect",
      "got": "incorrect",
      "pass": true,
      "status": "incorrect",
      "feedback": "max abs err 9.573e+03 on (37, 4097)/torch.float16 scale~288 (113701 elems over tol 2.0e-03/2.0e-02) \u2014 likely a reduction/stability bug, not a shape bug",
      "correct": false,
      "n_shapes_passed": 0,
      "max_abs_err": 9572.875,
      "latency_ms": 0.0,
      "eager_ms": 0.0,
      "compile_ms": 0.0,
      "maxauto_ms": 0.0,
      "speedup_eager": 0.0,
      "speedup_compile": 0.0,
      "speedup_maxauto": 0.0
    },
    {
      "spec": "entropy",
      "kernel": "entropy_wrong.py",
      "label": "NEGATIVE-CONTROL (no max-subtract)",
      "expect": "incorrect",
      "got": "incorrect",
      "pass": true,
      "status": "incorrect",
      "feedback": "max abs err nan on (37, 4097)/torch.float16 scale~288 (0 elems over tol 2.0e-03/2.0e-02) \u2014 likely a reduction/stability bug, not a shape bug",
      "correct": false,
      "n_shapes_passed": 0,
      "max_abs_err": NaN,
      "latency_ms": 0.0,
      "eager_ms": 0.0,
      "compile_ms": 0.0,
      "maxauto_ms": 0.0,
      "speedup_eager": 0.0,
      "speedup_compile": 0.0,
      "speedup_maxauto": 0.0
    },
    {
      "spec": "kl_div",
      "kernel": "kl_div_wrong.py",
      "label": "NEGATIVE-CONTROL (2nd lse not max-subtracted)",
      "expect": "incorrect",
      "got": "incorrect",
      "pass": true,
      "status": "incorrect",
      "feedback": "max abs err nan on (37, 4097)/torch.float16 scale~276 (0 elems over tol 2.0e-03/2.0e-02) \u2014 likely a reduction/stability bug, not a shape bug",
      "correct": false,
      "n_shapes_passed": 0,
      "max_abs_err": NaN,
      "latency_ms": 0.0,
      "eager_ms": 0.0,
      "compile_ms": 0.0,
      "maxauto_ms": 0.0,
      "speedup_eager": 0.0,
      "speedup_compile": 0.0,
      "speedup_maxauto": 0.0
    },
    {
      "spec": "softmax",
      "kernel": "softmax_cheat_shape.py",
      "label": "ANTI-GAMING (special-cases bench shape)",
      "expect": "incorrect",
      "got": "incorrect",
      "pass": true,
      "status": "incorrect",
      "feedback": "max abs err 5.120e+02 on (8192, 4096)/torch.float16 scale~6 (29374580 elems over tol 2.0e-03/2.0e-02) \u2014 likely a reduction/stability bug, not a shape bug",
      "correct": false,
      "n_shapes_passed": 3,
      "max_abs_err": 512.0242919921875,
      "latency_ms": 0.0,
      "eager_ms": 0.0,
      "compile_ms": 0.0,
      "maxauto_ms": 0.0,
      "speedup_eager": 0.0,
      "speedup_compile": 0.0,
      "speedup_maxauto": 0.0
    },
    {
      "spec": "softmax",
      "kernel": "softmax_cheat_memo.py",
      "label": "ANTI-GAMING (memoizes by input pointer)",
      "expect": "incorrect",
      "got": "incorrect",
      "pass": true,
      "status": "incorrect",
      "feedback": "bench-output verification FAILED: the timed output does not match the reference on the live input state (memoization/caching suspected)",
      "correct": false,
      "n_shapes_passed": 12,
      "max_abs_err": 0.0,
      "latency_ms": 0.0,
      "eager_ms": 0.0,
      "compile_ms": 0.0,
      "maxauto_ms": 0.0,
      "speedup_eager": 0.0,
      "speedup_compile": 0.0,
      "speedup_maxauto": 0.0
    },
    {
      "spec": "silu",
      "kernel": "silu_mutate.py",
      "label": "ANTI-GAMING (mutates input in-place)",
      "expect": "incorrect",
      "got": "incorrect",
      "pass": true,
      "status": "incorrect",
      "feedback": "kernel MUTATES its input ((37, 4097)/torch.float16) \u2014 run() must write a fresh output tensor",
      "correct": false,
      "n_shapes_passed": 0,
      "max_abs_err": 0.0,
      "latency_ms": 0.0,
      "eager_ms": 0.0,
      "compile_ms": 0.0,
      "maxauto_ms": 0.0,
      "speedup_eager": 0.0,
      "speedup_compile": 0.0,
      "speedup_maxauto": 0.0
    }
  ]
}